{
  "generated_at": "2026-06-01T09:51:39.642622+00:00",
  "count": 10,
  "tickers": [
    {
      "symbol": "AAPL",
      "company": "Apple Inc",
      "sector": "Technology",
      "price": 312.06,
      "change_pct": -0.144,
      "verdict": "WATCH-BUY",
      "composite": 0.452,
      "coverage": 0.65,
      "scores": {
        "fundamentals": 0.5,
        "technicals": 0.0,
        "sentiment": 0.376
      },
      "reasons": [
        "[fundamentals] P/E 37.4 (fair)",
        "[fundamentals] Revenue growth 12.8% YoY > 5%",
        "[fundamentals] Debt/Equity 0.80 < 1.5",
        "[technicals] technicals: unavailable (/stock/candle -> HTTP 403 (no access on this API plan). Some Finnhub free plans gate /stock/candle.)",
        "[sentiment] Headline sentiment +0.38 over 50 stories (38+ / 9-, VADER)"
      ],
      "flags": [
        "near_52wk_high"
      ],
      "alerts": [
        "Near 52-wk high (312.06 vs 315)"
      ],
      "details": {
        "technicals": {},
        "sentiment": {
          "source": "vader_headlines",
          "stories": 50,
          "avg": 0.376
        }
      },
      "sources": {
        "primary": "finnhub"
      },
      "fundamentals": [
        {
          "key": "pe",
          "label": "P/E",
          "value": 37.3921,
          "display": "37.4\u00d7",
          "sector_benchmark": 26.7105,
          "word": "expensive",
          "tone": "bad"
        },
        {
          "key": "pb",
          "label": "P/B",
          "value": 34.0011,
          "display": "34.0\u00d7",
          "sector_benchmark": 6.6336,
          "word": "expensive",
          "tone": "bad"
        },
        {
          "key": "ps",
          "label": "P/S",
          "value": 10.1527,
          "display": "10.2\u00d7",
          "sector_benchmark": 10.5085,
          "word": "in line",
          "tone": "neutral"
        },
        {
          "key": "gross_margin",
          "label": "Gross margin",
          "value": 47.86,
          "display": "47.9%",
          "sector_benchmark": 68.31,
          "word": "weak",
          "tone": "bad"
        },
        {
          "key": "net_margin",
          "label": "Net margin",
          "value": 27.15,
          "display": "27.1%",
          "sector_benchmark": 39.34,
          "word": "weak",
          "tone": "bad"
        },
        {
          "key": "roe",
          "label": "ROE",
          "value": 146.69,
          "display": "146.7%",
          "sector_benchmark": 33.13,
          "word": "strong",
          "tone": "good"
        },
        {
          "key": "roa",
          "label": "ROA",
          "value": 34.02,
          "display": "34.0%",
          "sector_benchmark": 19.15,
          "word": "strong",
          "tone": "good"
        },
        {
          "key": "current_ratio",
          "label": "Current ratio",
          "value": 1.0704,
          "display": "1.1\u00d7",
          "sector_benchmark": 1.2829,
          "word": "weak",
          "tone": "bad"
        },
        {
          "key": "debt_to_equity",
          "label": "Debt/Equity",
          "value": 0.7955,
          "display": "0.8\u00d7",
          "sector_benchmark": 0.249,
          "word": "heavy",
          "tone": "bad"
        },
        {
          "key": "rev_growth",
          "label": "Rev growth YoY",
          "value": 12.76,
          "display": "12.8%",
          "sector_benchmark": 17.87,
          "word": "weak",
          "tone": "bad"
        },
        {
          "key": "dividend_yield",
          "label": "Dividend yield",
          "value": 0.3461,
          "display": "0.3%",
          "sector_benchmark": 0.8085,
          "word": "low",
          "tone": "neutral"
        }
      ],
      "peers_in_sector": 1
    },
    {
      "symbol": "MSFT",
      "company": "Microsoft Corp",
      "sector": "Technology",
      "price": 450.24,
      "change_pct": 5.4451,
      "verdict": "WATCH-BUY",
      "composite": 0.451,
      "coverage": 0.65,
      "scores": {
        "fundamentals": 0.5,
        "technicals": 0.0,
        "sentiment": 0.372
      },
      "reasons": [
        "[fundamentals] P/E 26.7 (fair)",
        "[fundamentals] Revenue growth 17.9% YoY > 5%",
        "[fundamentals] Debt/Equity 0.25 < 1.5",
        "[technicals] technicals: unavailable (/stock/candle -> HTTP 403 (no access on this API plan). Some Finnhub free plans gate /stock/candle.)",
        "[sentiment] Headline sentiment +0.37 over 50 stories (39+ / 10-, VADER)"
      ],
      "flags": [
        "big_daily_move"
      ],
      "alerts": [
        "Daily move +5.4% (>= 5%)"
      ],
      "details": {
        "technicals": {},
        "sentiment": {
          "source": "vader_headlines",
          "stories": 50,
          "avg": 0.372
        }
      },
      "sources": {
        "primary": "finnhub"
      },
      "fundamentals": [
        {
          "key": "pe",
          "label": "P/E",
          "value": 26.7105,
          "display": "26.7\u00d7",
          "sector_benchmark": 37.3921,
          "word": "cheap",
          "tone": "good"
        },
        {
          "key": "pb",
          "label": "P/B",
          "value": 6.6336,
          "display": "6.6\u00d7",
          "sector_benchmark": 34.0011,
          "word": "cheap",
          "tone": "good"
        },
        {
          "key": "ps",
          "label": "P/S",
          "value": 10.5085,
          "display": "10.5\u00d7",
          "sector_benchmark": 10.1527,
          "word": "in line",
          "tone": "neutral"
        },
        {
          "key": "gross_margin",
          "label": "Gross margin",
          "value": 68.31,
          "display": "68.3%",
          "sector_benchmark": 47.86,
          "word": "strong",
          "tone": "good"
        },
        {
          "key": "net_margin",
          "label": "Net margin",
          "value": 39.34,
          "display": "39.3%",
          "sector_benchmark": 27.15,
          "word": "strong",
          "tone": "good"
        },
        {
          "key": "roe",
          "label": "ROE",
          "value": 33.13,
          "display": "33.1%",
          "sector_benchmark": 146.69,
          "word": "weak",
          "tone": "bad"
        },
        {
          "key": "roa",
          "label": "ROA",
          "value": 19.15,
          "display": "19.1%",
          "sector_benchmark": 34.02,
          "word": "weak",
          "tone": "bad"
        },
        {
          "key": "current_ratio",
          "label": "Current ratio",
          "value": 1.2829,
          "display": "1.3\u00d7",
          "sector_benchmark": 1.0704,
          "word": "strong",
          "tone": "good"
        },
        {
          "key": "debt_to_equity",
          "label": "Debt/Equity",
          "value": 0.249,
          "display": "0.2\u00d7",
          "sector_benchmark": 0.7955,
          "word": "lean",
          "tone": "good"
        },
        {
          "key": "rev_growth",
          "label": "Rev growth YoY",
          "value": 17.87,
          "display": "17.9%",
          "sector_benchmark": 12.76,
          "word": "strong",
          "tone": "good"
        },
        {
          "key": "dividend_yield",
          "label": "Dividend yield",
          "value": 0.8085,
          "display": "0.8%",
          "sector_benchmark": 0.3461,
          "word": "high",
          "tone": "neutral"
        }
      ],
      "peers_in_sector": 1
    },
    {
      "symbol": "GOOGL",
      "company": "Alphabet Inc",
      "sector": "Media",
      "price": 380.34,
      "change_pct": -2.5094,
      "verdict": "WATCH-BUY",
      "composite": 0.437,
      "coverage": 0.65,
      "scores": {
        "fundamentals": 0.5,
        "technicals": 0.0,
        "sentiment": 0.337
      },
      "reasons": [
        "[fundamentals] P/E 28.8 (fair)",
        "[fundamentals] Revenue growth 17.4% YoY > 5%",
        "[fundamentals] Debt/Equity 0.16 < 1.5",
        "[technicals] technicals: unavailable (/stock/candle -> HTTP 403 (no access on this API plan). Some Finnhub free plans gate /stock/candle.)",
        "[sentiment] Headline sentiment +0.34 over 50 stories (37+ / 12-, VADER)"
      ],
      "flags": [],
      "alerts": [],
      "details": {
        "technicals": {},
        "sentiment": {
          "source": "vader_headlines",
          "stories": 50,
          "avg": 0.337
        }
      },
      "sources": {
        "primary": "finnhub"
      },
      "fundamentals": [
        {
          "key": "pe",
          "label": "P/E",
          "value": 28.7639,
          "display": "28.8\u00d7",
          "sector_benchmark": 22.7461,
          "word": "expensive",
          "tone": "bad"
        },
        {
          "key": "pb",
          "label": "P/B",
          "value": 7.2581,
          "display": "7.3\u00d7",
          "sector_benchmark": 5.9391,
          "word": "expensive",
          "tone": "bad"
        },
        {
          "key": "ps",
          "label": "P/S",
          "value": 10.907,
          "display": "10.9\u00d7",
          "sector_benchmark": 7.4691,
          "word": "expensive",
          "tone": "bad"
        },
        {
          "key": "gross_margin",
          "label": "Gross margin",
          "value": 60.37,
          "display": "60.4%",
          "sector_benchmark": 81.94,
          "word": "weak",
          "tone": "bad"
        },
        {
          "key": "net_margin",
          "label": "Net margin",
          "value": 37.92,
          "display": "37.9%",
          "sector_benchmark": 32.84,
          "word": "strong",
          "tone": "good"
        },
        {
          "key": "roe",
          "label": "ROE",
          "value": 38.98,
          "display": "39.0%",
          "sector_benchmark": 33.22,
          "word": "strong",
          "tone": "good"
        },
        {
          "key": "roa",
          "label": "ROA",
          "value": 27.41,
          "display": "27.4%",
          "sector_benchmark": 20.76,
          "word": "strong",
          "tone": "good"
        },
        {
          "key": "current_ratio",
          "label": "Current ratio",
          "value": 1.9224,
          "display": "1.9\u00d7",
          "sector_benchmark": 2.3478,
          "word": "weak",
          "tone": "bad"
        },
        {
          "key": "debt_to_equity",
          "label": "Debt/Equity",
          "value": 0.1619,
          "display": "0.2\u00d7",
          "sector_benchmark": 0.2411,
          "word": "lean",
          "tone": "good"
        },
        {
          "key": "rev_growth",
          "label": "Rev growth YoY",
          "value": 17.45,
          "display": "17.4%",
          "sector_benchmark": 26.18,
          "word": "weak",
          "tone": "bad"
        },
        {
          "key": "dividend_yield",
          "label": "Dividend yield",
          "value": 0.2314,
          "display": "0.2%",
          "sector_benchmark": 0.332,
          "word": "low",
          "tone": "neutral"
        }
      ],
      "peers_in_sector": 1
    },
    {
      "symbol": "AMZN",
      "company": "Amazon.com Inc",
      "sector": "Retail",
      "price": 270.64,
      "change_pct": -1.2263,
      "verdict": "WATCH-BUY",
      "composite": 0.42,
      "coverage": 0.65,
      "scores": {
        "fundamentals": 0.5,
        "technicals": 0.0,
        "sentiment": 0.292
      },
      "reasons": [
        "[fundamentals] P/E 32.1 (fair)",
        "[fundamentals] Revenue growth 14.2% YoY > 5%",
        "[fundamentals] Debt/Equity 0.27 < 1.5",
        "[technicals] technicals: unavailable (/stock/candle -> HTTP 403 (no access on this API plan). Some Finnhub free plans gate /stock/candle.)",
        "[sentiment] Headline sentiment +0.29 over 50 stories (36+ / 12-, VADER)"
      ],
      "flags": [],
      "alerts": [],
      "details": {
        "technicals": {},
        "sentiment": {
          "source": "vader_headlines",
          "stories": 50,
          "avg": 0.292
        }
      },
      "sources": {
        "primary": "finnhub"
      },
      "fundamentals": [
        {
          "key": "pe",
          "label": "P/E",
          "value": 32.0635,
          "display": "32.1\u00d7",
          "sector_benchmark": null,
          "word": null,
          "tone": null
        },
        {
          "key": "pb",
          "label": "P/B",
          "value": 5.0684,
          "display": "5.1\u00d7",
          "sector_benchmark": null,
          "word": null,
          "tone": null
        },
        {
          "key": "ps",
          "label": "P/S",
          "value": 3.9195,
          "display": "3.9\u00d7",
          "sector_benchmark": null,
          "word": null,
          "tone": null
        },
        {
          "key": "gross_margin",
          "label": "Gross margin",
          "value": 50.6,
          "display": "50.6%",
          "sector_benchmark": null,
          "word": null,
          "tone": null
        },
        {
          "key": "net_margin",
          "label": "Net margin",
          "value": 12.22,
          "display": "12.2%",
          "sector_benchmark": null,
          "word": null,
          "tone": null
        },
        {
          "key": "roe",
          "label": "ROE",
          "value": 23.34,
          "display": "23.3%",
          "sector_benchmark": null,
          "word": null,
          "tone": null
        },
        {
          "key": "roa",
          "label": "ROA",
          "value": 11.55,
          "display": "11.6%",
          "sector_benchmark": null,
          "word": null,
          "tone": null
        },
        {
          "key": "current_ratio",
          "label": "Current ratio",
          "value": 1.1772,
          "display": "1.2\u00d7",
          "sector_benchmark": null,
          "word": null,
          "tone": null
        },
        {
          "key": "debt_to_equity",
          "label": "Debt/Equity",
          "value": 0.2695,
          "display": "0.3\u00d7",
          "sector_benchmark": null,
          "word": null,
          "tone": null
        },
        {
          "key": "rev_growth",
          "label": "Rev growth YoY",
          "value": 14.22,
          "display": "14.2%",
          "sector_benchmark": null,
          "word": null,
          "tone": null
        }
      ],
      "peers_in_sector": 0
    },
    {
      "symbol": "NVDA",
      "company": "NVIDIA Corp",
      "sector": "Semiconductors",
      "price": 211.14,
      "change_pct": -1.4516,
      "verdict": "WATCH-BUY",
      "composite": 0.484,
      "coverage": 0.65,
      "scores": {
        "fundamentals": 0.5,
        "technicals": 0.0,
        "sentiment": 0.458
      },
      "reasons": [
        "[fundamentals] P/E 32.0 (fair)",
        "[fundamentals] Revenue growth 70.7% YoY > 5%",
        "[fundamentals] Debt/Equity 0.04 < 1.5",
        "[technicals] technicals: unavailable (/stock/candle -> HTTP 403 (no access on this API plan). Some Finnhub free plans gate /stock/candle.)",
        "[sentiment] Headline sentiment +0.46 over 50 stories (39+ / 8-, VADER)"
      ],
      "flags": [],
      "alerts": [],
      "details": {
        "technicals": {},
        "sentiment": {
          "source": "vader_headlines",
          "stories": 50,
          "avg": 0.458
        }
      },
      "sources": {
        "primary": "finnhub"
      },
      "fundamentals": [
        {
          "key": "pe",
          "label": "P/E",
          "value": 32.0124,
          "display": "32.0\u00d7",
          "sector_benchmark": null,
          "word": null,
          "tone": null
        },
        {
          "key": "pb",
          "label": "P/B",
          "value": 26.9275,
          "display": "26.9\u00d7",
          "sector_benchmark": null,
          "word": null,
          "tone": null
        },
        {
          "key": "ps",
          "label": "P/S",
          "value": 20.1569,
          "display": "20.2\u00d7",
          "sector_benchmark": null,
          "word": null,
          "tone": null
        },
        {
          "key": "gross_margin",
          "label": "Gross margin",
          "value": 74.15,
          "display": "74.2%",
          "sector_benchmark": null,
          "word": null,
          "tone": null
        },
        {
          "key": "net_margin",
          "label": "Net margin",
          "value": 62.97,
          "display": "63.0%",
          "sector_benchmark": null,
          "word": null,
          "tone": null
        },
        {
          "key": "roe",
          "label": "ROE",
          "value": 111.66,
          "display": "111.7%",
          "sector_benchmark": null,
          "word": null,
          "tone": null
        },
        {
          "key": "roa",
          "label": "ROA",
          "value": 83.11,
          "display": "83.1%",
          "sector_benchmark": null,
          "word": null,
          "tone": null
        },
        {
          "key": "current_ratio",
          "label": "Current ratio",
          "value": 3.4408,
          "display": "3.4\u00d7",
          "sector_benchmark": null,
          "word": null,
          "tone": null
        },
        {
          "key": "debt_to_equity",
          "label": "Debt/Equity",
          "value": 0.0433,
          "display": "0.0\u00d7",
          "sector_benchmark": null,
          "word": null,
          "tone": null
        },
        {
          "key": "rev_growth",
          "label": "Rev growth YoY",
          "value": 70.68,
          "display": "70.7%",
          "sector_benchmark": null,
          "word": null,
          "tone": null
        },
        {
          "key": "dividend_yield",
          "label": "Dividend yield",
          "value": 0.4736,
          "display": "0.5%",
          "sector_benchmark": null,
          "word": null,
          "tone": null
        }
      ],
      "peers_in_sector": 0
    },
    {
      "symbol": "META",
      "company": "Meta Platforms Inc",
      "sector": "Media",
      "price": 632.51,
      "change_pct": -0.4376,
      "verdict": "WATCH-BUY",
      "composite": 0.653,
      "coverage": 0.65,
      "scores": {
        "fundamentals": 0.9,
        "technicals": 0.0,
        "sentiment": 0.257
      },
      "reasons": [
        "[fundamentals] P/E 22.7 < 25 (attractive)",
        "[fundamentals] Revenue growth 26.2% YoY > 5%",
        "[fundamentals] Debt/Equity 0.24 < 1.5",
        "[technicals] technicals: unavailable (/stock/candle -> HTTP 403 (no access on this API plan). Some Finnhub free plans gate /stock/candle.)",
        "[sentiment] Headline sentiment +0.26 over 50 stories (35+ / 13-, VADER)"
      ],
      "flags": [],
      "alerts": [],
      "details": {
        "technicals": {},
        "sentiment": {
          "source": "vader_headlines",
          "stories": 50,
          "avg": 0.257
        }
      },
      "sources": {
        "primary": "finnhub"
      },
      "fundamentals": [
        {
          "key": "pe",
          "label": "P/E",
          "value": 22.7461,
          "display": "22.7\u00d7",
          "sector_benchmark": 28.7639,
          "word": "cheap",
          "tone": "good"
        },
        {
          "key": "pb",
          "label": "P/B",
          "value": 5.9391,
          "display": "5.9\u00d7",
          "sector_benchmark": 7.2581,
          "word": "cheap",
          "tone": "good"
        },
        {
          "key": "ps",
          "label": "P/S",
          "value": 7.4691,
          "display": "7.5\u00d7",
          "sector_benchmark": 10.907,
          "word": "cheap",
          "tone": "good"
        },
        {
          "key": "gross_margin",
          "label": "Gross margin",
          "value": 81.94,
          "display": "81.9%",
          "sector_benchmark": 60.37,
          "word": "strong",
          "tone": "good"
        },
        {
          "key": "net_margin",
          "label": "Net margin",
          "value": 32.84,
          "display": "32.8%",
          "sector_benchmark": 37.92,
          "word": "weak",
          "tone": "bad"
        },
        {
          "key": "roe",
          "label": "ROE",
          "value": 33.22,
          "display": "33.2%",
          "sector_benchmark": 38.98,
          "word": "weak",
          "tone": "bad"
        },
        {
          "key": "roa",
          "label": "ROA",
          "value": 20.76,
          "display": "20.8%",
          "sector_benchmark": 27.41,
          "word": "weak",
          "tone": "bad"
        },
        {
          "key": "current_ratio",
          "label": "Current ratio",
          "value": 2.3478,
          "display": "2.3\u00d7",
          "sector_benchmark": 1.9224,
          "word": "strong",
          "tone": "good"
        },
        {
          "key": "debt_to_equity",
          "label": "Debt/Equity",
          "value": 0.2411,
          "display": "0.2\u00d7",
          "sector_benchmark": 0.1619,
          "word": "heavy",
          "tone": "bad"
        },
        {
          "key": "rev_growth",
          "label": "Rev growth YoY",
          "value": 26.18,
          "display": "26.2%",
          "sector_benchmark": 17.45,
          "word": "strong",
          "tone": "good"
        },
        {
          "key": "dividend_yield",
          "label": "Dividend yield",
          "value": 0.332,
          "display": "0.3%",
          "sector_benchmark": 0.2314,
          "word": "high",
          "tone": "neutral"
        }
      ],
      "peers_in_sector": 1
    },
    {
      "symbol": "TSLA",
      "company": "Tesla Inc",
      "sector": "Automobiles",
      "price": 435.79,
      "change_pct": -1.4273,
      "verdict": "NEUTRAL",
      "composite": -0.034,
      "coverage": 0.65,
      "scores": {
        "fundamentals": -0.3,
        "technicals": 0.0,
        "sentiment": 0.392
      },
      "reasons": [
        "[fundamentals] P/E 423.8 > 40 (rich)",
        "[fundamentals] Revenue growth 2.2% YoY (soft)",
        "[fundamentals] Debt/Equity 0.11 < 1.5",
        "[technicals] technicals: unavailable (/stock/candle -> HTTP 403 (no access on this API plan). Some Finnhub free plans gate /stock/candle.)",
        "[sentiment] Headline sentiment +0.39 over 50 stories (37+ / 5-, VADER)"
      ],
      "flags": [
        "high_pe"
      ],
      "alerts": [],
      "details": {
        "technicals": {},
        "sentiment": {
          "source": "vader_headlines",
          "stories": 50,
          "avg": 0.392
        }
      },
      "sources": {
        "primary": "finnhub"
      },
      "fundamentals": [
        {
          "key": "pe",
          "label": "P/E",
          "value": 423.7977,
          "display": "423.8\u00d7",
          "sector_benchmark": null,
          "word": null,
          "tone": null
        },
        {
          "key": "pb",
          "label": "P/B",
          "value": 16.5838,
          "display": "16.6\u00d7",
          "sector_benchmark": null,
          "word": null,
          "tone": null
        },
        {
          "key": "ps",
          "label": "P/S",
          "value": 16.7217,
          "display": "16.7\u00d7",
          "sector_benchmark": null,
          "word": null,
          "tone": null
        },
        {
          "key": "gross_margin",
          "label": "Gross margin",
          "value": 19.07,
          "display": "19.1%",
          "sector_benchmark": null,
          "word": null,
          "tone": null
        },
        {
          "key": "net_margin",
          "label": "Net margin",
          "value": 3.95,
          "display": "4.0%",
          "sector_benchmark": null,
          "word": null,
          "tone": null
        },
        {
          "key": "roe",
          "label": "ROE",
          "value": 4.77,
          "display": "4.8%",
          "sector_benchmark": null,
          "word": null,
          "tone": null
        },
        {
          "key": "roa",
          "label": "ROA",
          "value": 2.84,
          "display": "2.8%",
          "sector_benchmark": null,
          "word": null,
          "tone": null
        },
        {
          "key": "current_ratio",
          "label": "Current ratio",
          "value": 2.0431,
          "display": "2.0\u00d7",
          "sector_benchmark": null,
          "word": null,
          "tone": null
        },
        {
          "key": "debt_to_equity",
          "label": "Debt/Equity",
          "value": 0.1097,
          "display": "0.1\u00d7",
          "sector_benchmark": null,
          "word": null,
          "tone": null
        },
        {
          "key": "rev_growth",
          "label": "Rev growth YoY",
          "value": 2.25,
          "display": "2.2%",
          "sector_benchmark": null,
          "word": null,
          "tone": null
        }
      ],
      "peers_in_sector": 0
    },
    {
      "symbol": "JPM",
      "company": "JPMorgan Chase & Co",
      "sector": "Banking",
      "price": 299.31,
      "change_pct": 0.8695,
      "verdict": "WATCH-BUY",
      "composite": 0.43,
      "coverage": 0.65,
      "scores": {
        "fundamentals": 0.5,
        "technicals": 0.0,
        "sentiment": 0.317
      },
      "reasons": [
        "[fundamentals] P/E 13.6 < 25 (attractive)",
        "[fundamentals] Revenue growth 109.0% YoY > 5%",
        "[fundamentals] Debt/Equity 3.39 > 1.5 (leveraged)",
        "[technicals] technicals: unavailable (/stock/candle -> HTTP 403 (no access on this API plan). Some Finnhub free plans gate /stock/candle.)",
        "[sentiment] Headline sentiment +0.32 over 50 stories (32+ / 12-, VADER)"
      ],
      "flags": [
        "high_leverage"
      ],
      "alerts": [],
      "details": {
        "technicals": {},
        "sentiment": {
          "source": "vader_headlines",
          "stories": 50,
          "avg": 0.317
        }
      },
      "sources": {
        "primary": "finnhub"
      },
      "fundamentals": [
        {
          "key": "pe",
          "label": "P/E",
          "value": 13.6166,
          "display": "13.6\u00d7",
          "sector_benchmark": null,
          "word": null,
          "tone": null
        },
        {
          "key": "pb",
          "label": "P/B",
          "value": 2.1674,
          "display": "2.2\u00d7",
          "sector_benchmark": null,
          "word": null,
          "tone": null
        },
        {
          "key": "ps",
          "label": "P/S",
          "value": 2.896,
          "display": "2.9\u00d7",
          "sector_benchmark": null,
          "word": null,
          "tone": null
        },
        {
          "key": "net_margin",
          "label": "Net margin",
          "value": 33.2645,
          "display": "33.3%",
          "sector_benchmark": null,
          "word": null,
          "tone": null
        },
        {
          "key": "roe",
          "label": "ROE",
          "value": 16.32,
          "display": "16.3%",
          "sector_benchmark": null,
          "word": null,
          "tone": null
        },
        {
          "key": "roa",
          "label": "ROA",
          "value": 1.28,
          "display": "1.3%",
          "sector_benchmark": null,
          "word": null,
          "tone": null
        },
        {
          "key": "debt_to_equity",
          "label": "Debt/Equity",
          "value": 3.3882,
          "display": "3.4\u00d7",
          "sector_benchmark": null,
          "word": null,
          "tone": null
        },
        {
          "key": "rev_growth",
          "label": "Rev growth YoY",
          "value": 108.9793,
          "display": "109.0%",
          "sector_benchmark": null,
          "word": null,
          "tone": null
        },
        {
          "key": "dividend_yield",
          "label": "Dividend yield",
          "value": 2.0046,
          "display": "2.0%",
          "sector_benchmark": null,
          "word": null,
          "tone": null
        }
      ],
      "peers_in_sector": 0
    },
    {
      "symbol": "V",
      "company": "Visa Inc",
      "sector": "Financial Services",
      "price": 326.36,
      "change_pct": 0.4339,
      "verdict": "WATCH-BUY",
      "composite": 0.437,
      "coverage": 0.65,
      "scores": {
        "fundamentals": 0.5,
        "technicals": 0.0,
        "sentiment": 0.337
      },
      "reasons": [
        "[fundamentals] P/E 27.6 (fair)",
        "[fundamentals] Revenue growth 14.4% YoY > 5%",
        "[fundamentals] Debt/Equity 0.67 < 1.5",
        "[technicals] technicals: unavailable (/stock/candle -> HTTP 403 (no access on this API plan). Some Finnhub free plans gate /stock/candle.)",
        "[sentiment] Headline sentiment +0.34 over 50 stories (33+ / 9-, VADER)"
      ],
      "flags": [],
      "alerts": [],
      "details": {
        "technicals": {},
        "sentiment": {
          "source": "vader_headlines",
          "stories": 50,
          "avg": 0.337
        }
      },
      "sources": {
        "primary": "finnhub"
      },
      "fundamentals": [
        {
          "key": "pe",
          "label": "P/E",
          "value": 27.5833,
          "display": "27.6\u00d7",
          "sector_benchmark": null,
          "word": null,
          "tone": null
        },
        {
          "key": "pb",
          "label": "P/B",
          "value": 16.1541,
          "display": "16.2\u00d7",
          "sector_benchmark": null,
          "word": null,
          "tone": null
        },
        {
          "key": "ps",
          "label": "P/S",
          "value": 14.2548,
          "display": "14.3\u00d7",
          "sector_benchmark": null,
          "word": null,
          "tone": null
        },
        {
          "key": "gross_margin",
          "label": "Gross margin",
          "value": 81.29,
          "display": "81.3%",
          "sector_benchmark": null,
          "word": null,
          "tone": null
        },
        {
          "key": "net_margin",
          "label": "Net margin",
          "value": 51.68,
          "display": "51.7%",
          "sector_benchmark": null,
          "word": null,
          "tone": null
        },
        {
          "key": "roe",
          "label": "ROE",
          "value": 58.9,
          "display": "58.9%",
          "sector_benchmark": null,
          "word": null,
          "tone": null
        },
        {
          "key": "roa",
          "label": "ROA",
          "value": 22.72,
          "display": "22.7%",
          "sector_benchmark": null,
          "word": null,
          "tone": null
        },
        {
          "key": "current_ratio",
          "label": "Current ratio",
          "value": 1.0877,
          "display": "1.1\u00d7",
          "sector_benchmark": null,
          "word": null,
          "tone": null
        },
        {
          "key": "debt_to_equity",
          "label": "Debt/Equity",
          "value": 0.6723,
          "display": "0.7\u00d7",
          "sector_benchmark": null,
          "word": null,
          "tone": null
        },
        {
          "key": "rev_growth",
          "label": "Rev growth YoY",
          "value": 14.37,
          "display": "14.4%",
          "sector_benchmark": null,
          "word": null,
          "tone": null
        },
        {
          "key": "dividend_yield",
          "label": "Dividend yield",
          "value": 0.8367,
          "display": "0.8%",
          "sector_benchmark": null,
          "word": null,
          "tone": null
        }
      ],
      "peers_in_sector": 0
    },
    {
      "symbol": "JNJ",
      "company": "Johnson & Johnson",
      "sector": "Pharmaceuticals",
      "price": 225.33,
      "change_pct": -2.37,
      "verdict": "WATCH-BUY",
      "composite": 0.433,
      "coverage": 0.65,
      "scores": {
        "fundamentals": 0.5,
        "technicals": 0.0,
        "sentiment": 0.327
      },
      "reasons": [
        "[fundamentals] P/E 25.8 (fair)",
        "[fundamentals] Revenue growth 7.9% YoY > 5%",
        "[fundamentals] Debt/Equity 0.68 < 1.5",
        "[technicals] technicals: unavailable (/stock/candle -> HTTP 403 (no access on this API plan). Some Finnhub free plans gate /stock/candle.)",
        "[sentiment] Headline sentiment +0.33 over 50 stories (36+ / 11-, VADER)"
      ],
      "flags": [],
      "alerts": [],
      "details": {
        "technicals": {},
        "sentiment": {
          "source": "vader_headlines",
          "stories": 50,
          "avg": 0.327
        }
      },
      "sources": {
        "primary": "finnhub"
      },
      "fundamentals": [
        {
          "key": "pe",
          "label": "P/E",
          "value": 25.7803,
          "display": "25.8\u00d7",
          "sector_benchmark": null,
          "word": null,
          "tone": null
        },
        {
          "key": "pb",
          "label": "P/B",
          "value": 7.1942,
          "display": "7.2\u00d7",
          "sector_benchmark": null,
          "word": null,
          "tone": null
        },
        {
          "key": "ps",
          "label": "P/S",
          "value": 5.629,
          "display": "5.6\u00d7",
          "sector_benchmark": null,
          "word": null,
          "tone": null
        },
        {
          "key": "gross_margin",
          "label": "Gross margin",
          "value": 67.95,
          "display": "68.0%",
          "sector_benchmark": null,
          "word": null,
          "tone": null
        },
        {
          "key": "net_margin",
          "label": "Net margin",
          "value": 21.83,
          "display": "21.8%",
          "sector_benchmark": null,
          "word": null,
          "tone": null
        },
        {
          "key": "roe",
          "label": "ROE",
          "value": 26.26,
          "display": "26.3%",
          "sector_benchmark": null,
          "word": null,
          "tone": null
        },
        {
          "key": "roa",
          "label": "ROA",
          "value": 10.7,
          "display": "10.7%",
          "sector_benchmark": null,
          "word": null,
          "tone": null
        },
        {
          "key": "current_ratio",
          "label": "Current ratio",
          "value": 1.0252,
          "display": "1.0\u00d7",
          "sector_benchmark": null,
          "word": null,
          "tone": null
        },
        {
          "key": "debt_to_equity",
          "label": "Debt/Equity",
          "value": 0.6773,
          "display": "0.7\u00d7",
          "sector_benchmark": null,
          "word": null,
          "tone": null
        },
        {
          "key": "rev_growth",
          "label": "Rev growth YoY",
          "value": 7.87,
          "display": "7.9%",
          "sector_benchmark": null,
          "word": null,
          "tone": null
        },
        {
          "key": "dividend_yield",
          "label": "Dividend yield",
          "value": 2.3787,
          "display": "2.4%",
          "sector_benchmark": null,
          "word": null,
          "tone": null
        }
      ],
      "peers_in_sector": 0
    }
  ]
}